{"IcoMoonType":"selection","icons":[{"icon":{"paths":["M512 1024c-136.76 0-265.334-53.258-362.040-149.96-96.702-96.706-149.96-225.28-149.96-362.040 0-96.838 27.182-191.134 78.606-272.692 50-79.296 120.664-143.372 204.356-185.3l43 85.832c-68.038 34.084-125.492 86.186-166.15 150.67-41.746 66.208-63.812 142.798-63.812 221.49 0 229.382 186.618 416 416 416s416-186.618 416-416c0-78.692-22.066-155.282-63.81-221.49-40.66-64.484-98.114-116.584-166.15-150.67l43-85.832c83.692 41.928 154.358 106.004 204.356 185.3 51.422 81.558 78.604 175.854 78.604 272.692 0 136.76-53.258 265.334-149.96 362.040-96.706 96.702-225.28 149.96-362.040 149.96z"],"attrs":[{}],"isMulticolor":false,"isMulticolor2":false,"tags":["spinner","loading","loading-wheel","busy","wait"],"grid":16},"attrs":[{}],"properties":{"order":64,"id":3,"prevSize":32,"code":59648,"name":"spinner"},"setIdx":1,"setId":1,"iconIdx":0},{"icon":{"paths":["M512 820c106 0 200-56 256-138-2-84-172-132-256-132-86 0-254 48-256 132 56 82 150 138 256 138zM512 214c-70 0-128 58-128 128s58 128 128 128 128-58 128-128-58-128-128-128zM512 86c236 0 426 190 426 426s-190 426-426 426-426-190-426-426 190-426 426-426z"],"attrs":[],"isMulticolor":false,"isMulticolor2":false,"tags":["account_circle"],"defaultCode":59475,"grid":24},"attrs":[],"properties":{"ligatures":"account_circle","id":10,"order":45,"prevSize":24,"name":"account_circle","code":59475},"setIdx":2,"setId":0,"iconIdx":10},{"icon":{"paths":["M298 426h428l-214 214z"],"attrs":[],"isMulticolor":false,"isMulticolor2":false,"tags":["arrow_drop_down"],"defaultCode":58821,"grid":24},"attrs":[],"properties":{"ligatures":"arrow_drop_down","id":47,"order":46,"prevSize":24,"code":58821,"name":"arrow_drop_down"},"setIdx":2,"setId":0,"iconIdx":47},{"icon":{"paths":["M298 598l214-214 214 214h-428z"],"attrs":[],"isMulticolor":false,"isMulticolor2":false,"tags":["arrow_drop_up"],"defaultCode":58823,"grid":24},"attrs":[],"properties":{"ligatures":"arrow_drop_up","id":49,"order":47,"prevSize":24,"code":58823,"name":"arrow_drop_up"},"setIdx":2,"setId":0,"iconIdx":49},{"icon":{"paths":["M726 666l-154-154 154-154-60-60-154 154-154-154-60 60 154 154-154 154 60 60 154-154 154 154zM512 86c236 0 426 190 426 426s-190 426-426 426-426-190-426-426 190-426 426-426z"],"attrs":[],"isMulticolor":false,"isMulticolor2":false,"tags":["cancel"],"defaultCode":58825,"grid":24},"attrs":[],"properties":{"ligatures":"cancel","id":135,"order":51,"prevSize":24,"code":58825,"name":"cancel"},"setIdx":2,"setId":0,"iconIdx":135},{"icon":{"paths":["M768 342v-86h-512v86h512zM598 598v-86h-342v86h342zM256 384v86h512v-86h-512zM854 86c46 0 84 38 84 84v512c0 46-38 86-84 86h-598l-170 170v-768c0-46 38-84 84-84h684z"],"attrs":[],"isMulticolor":false,"isMulticolor2":false,"tags":["chat"],"defaultCode":57527,"grid":24},"attrs":[],"properties":{"ligatures":"chat","id":145,"order":67,"prevSize":24,"code":57527,"name":"chat"},"setIdx":2,"setId":0,"iconIdx":145},{"icon":{"paths":["M426 726l384-384-60-62-324 324-152-152-60 60zM512 86c236 0 426 190 426 426s-190 426-426 426-426-190-426-426 190-426 426-426z"],"attrs":[],"isMulticolor":false,"isMulticolor2":false,"tags":["check_circle"],"defaultCode":59500,"grid":24},"attrs":[],"properties":{"ligatures":"check_circle","id":151,"order":53,"prevSize":24,"code":59500,"name":"check_circle"},"setIdx":2,"setId":0,"iconIdx":151},{"icon":{"paths":["M810 274l-238 238 238 238-60 60-238-238-238 238-60-60 238-238-238-238 60-60 238 238 238-238z"],"attrs":[],"isMulticolor":false,"isMulticolor2":false,"tags":["close"],"defaultCode":58829,"grid":24},"attrs":[],"properties":{"ligatures":"clear, close","id":157,"order":50,"prevSize":24,"code":58829,"name":"close"},"setIdx":2,"setId":0,"iconIdx":157},{"icon":{"paths":["M662 170h148v86h-596v-86h148l44-42h212zM360 506l92 92-90 90 60 60 90-90 90 90 60-60-90-90 90-92-60-60-90 92-90-92zM256 810v-512h512v512c0 46-40 86-86 86h-340c-46 0-86-40-86-86z"],"attrs":[],"isMulticolor":false,"isMulticolor2":false,"tags":["delete_forever"],"defaultCode":59691,"grid":24},"attrs":[],"properties":{"ligatures":"delete_forever","id":203,"order":55,"prevSize":24,"name":"delete_forever","code":59691},"setIdx":2,"setId":0,"iconIdx":203},{"icon":{"paths":["M214 768h596v86h-596v-86zM384 682v-256h-170l298-298 298 298h-170v256h-256z"],"attrs":[],"isMulticolor":false,"isMulticolor2":false,"tags":["file_upload"],"defaultCode":58054,"grid":24},"attrs":[],"properties":{"ligatures":"file_upload","id":280,"order":48,"prevSize":24,"name":"file_upload","code":58054},"setIdx":2,"setId":0,"iconIdx":280},{"icon":{"paths":["M426 170c46 0 86 40 86 86s-40 86-86 86-84-40-84-86 38-86 84-86zM598 342c46 0 84 38 84 84s-38 86-84 86-86-40-86-86 40-84 86-84zM768 512c46 0 86 40 86 86s-40 84-86 84-86-38-86-84 40-86 86-86zM598 682c46 0 84 40 84 86s-38 86-84 86-86-40-86-86 40-86 86-86zM768 342c-46 0-86-40-86-86s40-86 86-86 86 40 86 86-40 86-86 86zM256 682c46 0 86 40 86 86s-40 86-86 86-86-40-86-86 40-86 86-86zM256 342c46 0 86 38 86 84s-40 86-86 86-86-40-86-86 40-84 86-84zM426 512c46 0 86 40 86 86s-40 84-86 84-84-38-84-84 38-86 84-86z"],"attrs":[],"isMulticolor":false,"isMulticolor2":false,"tags":["grain"],"defaultCode":58346,"grid":24},"attrs":[],"properties":{"ligatures":"grain","id":364,"order":59,"prevSize":24,"name":"grain","code":58346},"setIdx":2,"setId":0,"iconIdx":364},{"icon":{"paths":["M554 384v-86h-84v86h84zM554 726v-256h-84v256h84zM512 86c236 0 426 190 426 426s-190 426-426 426-426-190-426-426 190-426 426-426z"],"attrs":[],"isMulticolor":false,"isMulticolor2":false,"tags":["info"],"defaultCode":59534,"grid":24},"attrs":[],"properties":{"ligatures":"info","id":400,"order":68,"prevSize":24,"code":59534,"name":"info"},"setIdx":2,"setId":0,"iconIdx":400},{"icon":{"paths":["M554 384h236l-236-234v234zM256 86h342l256 256v512c0 46-40 84-86 84h-512c-46 0-86-38-86-84l2-684c0-46 38-84 84-84z"],"attrs":[],"isMulticolor":false,"isMulticolor2":false,"tags":["insert_drive_file"],"defaultCode":57933,"grid":24},"attrs":[],"properties":{"ligatures":"insert_drive_file","id":404,"order":58,"prevSize":24,"name":"insert_drive_file","code":57933},"setIdx":2,"setId":0,"iconIdx":404},{"icon":{"paths":["M316 334l196 196 196-196 60 60-256 256-256-256z"],"attrs":[],"isMulticolor":false,"isMulticolor2":false,"tags":["keyboard_arrow_down"],"defaultCode":58131,"grid":24},"attrs":[],"properties":{"ligatures":"keyboard_arrow_down","id":411,"order":69,"prevSize":24,"code":58131,"name":"keyboard_arrow_down"},"setIdx":2,"setId":0,"iconIdx":411},{"icon":{"paths":["M658 686l-60 60-256-256 256-256 60 60-196 196z"],"attrs":[],"isMulticolor":false,"isMulticolor2":false,"tags":["keyboard_arrow_left"],"defaultCode":58132,"grid":24},"attrs":[],"properties":{"ligatures":"keyboard_arrow_left","id":412,"order":70,"prevSize":24,"code":58132,"name":"keyboard_arrow_left"},"setIdx":2,"setId":0,"iconIdx":412},{"icon":{"paths":["M366 698l196-196-196-196 60-60 256 256-256 256z"],"attrs":[],"isMulticolor":false,"isMulticolor2":false,"tags":["keyboard_arrow_right"],"defaultCode":58133,"grid":24},"attrs":[],"properties":{"ligatures":"keyboard_arrow_right","id":413,"order":71,"prevSize":24,"code":58133,"name":"keyboard_arrow_right"},"setIdx":2,"setId":0,"iconIdx":413},{"icon":{"paths":["M316 658l-60-60 256-256 256 256-60 60-196-196z"],"attrs":[],"isMulticolor":false,"isMulticolor2":false,"tags":["keyboard_arrow_up"],"defaultCode":58134,"grid":24},"attrs":[],"properties":{"ligatures":"keyboard_arrow_up","id":414,"order":72,"prevSize":24,"code":58134,"name":"keyboard_arrow_up"},"setIdx":2,"setId":0,"iconIdx":414},{"icon":{"paths":["M512 682c46 0 86 40 86 86s-40 86-86 86-86-40-86-86 40-86 86-86zM512 426c46 0 86 40 86 86s-40 86-86 86-86-40-86-86 40-86 86-86zM512 342c-46 0-86-40-86-86s40-86 86-86 86 40 86 86-40 86-86 86z"],"attrs":[],"isMulticolor":false,"isMulticolor2":false,"tags":["more_vert"],"defaultCode":58836,"grid":24},"attrs":[],"properties":{"ligatures":"more_vert","id":502,"order":61,"prevSize":24,"code":58836,"name":"more_vert"},"setIdx":2,"setId":0,"iconIdx":502},{"icon":{"paths":["M754 270l100-100v300h-300l138-138c-46-46-110-76-180-76-142 0-256 114-256 256s114 256 256 256c112 0 208-70 242-170h88c-38 148-170 256-330 256-188 0-340-154-340-342s152-342 340-342c94 0 180 38 242 100z"],"attrs":[],"isMulticolor":false,"isMulticolor2":false,"tags":["refresh"],"defaultCode":58837,"grid":24},"attrs":[],"properties":{"ligatures":"refresh","id":616,"order":66,"prevSize":24,"code":58837,"name":"refresh"},"setIdx":2,"setId":0,"iconIdx":616},{"icon":{"paths":["M554 598v-172h-84v172h84zM554 768v-86h-84v86h84zM42 896l470-810 470 810h-940z"],"attrs":[],"isMulticolor":false,"isMulticolor2":false,"tags":["warning"],"defaultCode":57346,"grid":24},"attrs":[],"properties":{"ligatures":"report_problem, warning","id":632,"order":56,"prevSize":24,"code":57346,"name":"warning"},"setIdx":2,"setId":0,"iconIdx":632},{"icon":{"paths":["M512 128l470 256v342h-86v-296l-384 210-470-256zM214 562l298 164 298-164v172l-298 162-298-162v-172z"],"attrs":[],"isMulticolor":false,"isMulticolor2":false,"tags":["school"],"defaultCode":59404,"grid":24},"attrs":[],"properties":{"ligatures":"school","id":648,"order":60,"prevSize":24,"name":"school","code":59404},"setIdx":2,"setId":0,"iconIdx":648},{"icon":{"paths":["M768 342v-86h-342v86h342zM768 470v-86h-342v86h342zM640 598v-86h-214v86h214zM342 342v-86h-86v86h86zM342 470v-86h-86v86h86zM342 598v-86h-86v86h86zM854 86c46 0 84 38 84 84v512c0 46-38 86-84 86h-598l-170 170v-768c0-46 38-84 84-84h684z"],"attrs":[],"isMulticolor":false,"isMulticolor2":false,"tags":["speaker_notes"],"defaultCode":59597,"grid":24},"attrs":[],"properties":{"ligatures":"speaker_notes","id":712,"order":57,"prevSize":24,"name":"speaker_notes","code":59597},"setIdx":2,"setId":0,"iconIdx":712},{"icon":{"paths":["M170 214h684v84h-684v-84zM170 470v-86h684v86h-684zM170 810v-84h684v84h-684zM170 640v-86h684v86h-684z"],"attrs":[],"isMulticolor":false,"isMulticolor2":false,"tags":["view_headline"],"defaultCode":59630,"grid":24},"attrs":[],"properties":{"ligatures":"view_headline","id":807,"order":83,"prevSize":24,"code":59630,"name":"view_headline"},"setIdx":2,"setId":0,"iconIdx":807},{"icon":{"paths":["M682 214h214v256h-214v-256zM426 470v-256h214v256h-214zM682 768v-256h214v256h-214zM426 768v-256h214v256h-214zM170 768v-256h214v256h-214zM170 470v-256h214v256h-214z"],"attrs":[],"isMulticolor":false,"isMulticolor2":false,"tags":["view_module"],"defaultCode":59632,"grid":24},"attrs":[],"properties":{"ligatures":"view_module","id":809,"order":82,"prevSize":24,"code":59632,"name":"view_module"},"setIdx":2,"setId":0,"iconIdx":809},{"icon":{"paths":["M692 692l34-56-192-116v-222h-64v256zM512 86c234 0 426 192 426 426s-192 426-426 426-426-192-426-426 192-426 426-426z"],"attrs":[],"isMulticolor":false,"isMulticolor2":false,"tags":["watch_later"],"defaultCode":59684,"grid":24},"attrs":[],"properties":{"ligatures":"watch_later","id":825,"order":54,"prevSize":24,"name":"watch_later","code":59684},"setIdx":2,"setId":0,"iconIdx":825}],"height":1024,"metadata":{"name":"icomoon"},"preferences":{"showGlyphs":true,"showCodes":true,"showQuickUse":true,"showQuickUse2":true,"showSVGs":true,"fontPref":{"prefix":"icon-","metadata":{"fontFamily":"icomoon"},"metrics":{"emSize":1024,"baseline":6.25,"whitespace":50},"embed":false},"imagePref":{"prefix":"icon-","png":true,"useClassSelector":true,"color":0,"bgColor":16777215,"name":"icomoon","classSelector":".icon","height":32,"columns":16,"margin":16},"historySize":50,"showLiga":false}}